{
  "id": "free_txt",
  "type": "SharedSlice",
  "name": "FreeTxt",
  "description": "FreeTxt",
  "variations": [
    {
      "id": "default",
      "name": "Default",
      "docURL": "...",
      "version": "initial",
      "description": "Default",
      "imageUrl": "",
      "primary": {
        "heading": {
          "type": "StructuredText",
          "config": {
            "label": "Heading",
            "placeholder": "",
            "allowTargetBlank": true,
            "multi": "heading1,heading2,heading3,heading4,heading5"
          }
        },
        "body": {
          "type": "StructuredText",
          "config": {
            "label": "Body",
            "placeholder": "",
            "allowTargetBlank": true,
            "multi": "paragraph,preformatted,heading1,heading2,heading3,heading4,heading5,strong,em,hyperlink,image,embed,list-item,o-list-item,rtl,heading6"
          }
        }
      },
      "items": {}
    },
    {
      "id": "2Column",
      "name": "2 Column",
      "docURL": "...",
      "version": "initial",
      "description": "Default",
      "imageUrl": "",
      "primary": {
        "heading": {
          "type": "StructuredText",
          "config": {
            "label": "Heading",
            "placeholder": "",
            "allowTargetBlank": true,
            "multi": "heading1,heading2,heading3,heading4,heading5"
          }
        },
        "body": {
          "type": "StructuredText",
          "config": {
            "label": "Body",
            "placeholder": "",
            "allowTargetBlank": true,
            "multi": "paragraph,preformatted,heading1,heading2,heading3,heading4,heading5,strong,em,hyperlink,image,embed,list-item,o-list-item,rtl,heading6"
          }
        }
      },
      "items": {}
    },
    {
      "id": "3Column",
      "name": "3 Column",
      "docURL": "...",
      "version": "initial",
      "description": "Default",
      "imageUrl": "",
      "primary": {
        "heading": {
          "type": "StructuredText",
          "config": {
            "label": "Heading",
            "placeholder": "",
            "allowTargetBlank": true,
            "multi": "heading1,heading2,heading3,heading4,heading5"
          }
        },
        "body": {
          "type": "StructuredText",
          "config": {
            "label": "Body",
            "placeholder": "",
            "allowTargetBlank": true,
            "multi": "paragraph,preformatted,heading1,heading2,heading3,heading4,heading5,strong,em,hyperlink,image,embed,list-item,o-list-item,rtl,heading6"
          }
        }
      },
      "items": {}
    }
  ]
}